my_own_jim/__init__.py
my_own_jim/config.py
my_own_jim/core.py
my_own_jim/exceptions.py
my_own_jim/test_core.py
my_own_jim/test_exceptions.py
my_own_jim/test_utils.py
my_own_jim/utils.py
my_own_logs/__init__.py
my_own_logs/client_log_config.py
my_own_logs/decorators.py
my_own_logs/server_log_config.py
my_own_logs/test_decorators.py
my_own_messenger/.DS_Store
my_own_messenger/MyOwn.png
my_own_messenger/__init__.py
my_own_messenger/__main__.py
my_own_messenger/login_page.py
my_own_messenger/messenger.py
my_own_messenger/my_own_messenger.py
my_own_messenger/__pycache__/__init__.cpython-36.pyc
my_own_messenger/__pycache__/__main__.cpython-36.pyc
my_own_messenger/__pycache__/login_page.cpython-36.pyc
my_own_messenger/my_own_client/.DS_Store
my_own_messenger/my_own_client/__init__.py
my_own_messenger/my_own_client/__main__.py
my_own_messenger/my_own_client/client.py
my_own_messenger/my_own_client/client_gui.1.py
my_own_messenger/my_own_client/client_gui.py
my_own_messenger/my_own_client/client_view.py
my_own_messenger/my_own_client/generic-avatar.png
my_own_messenger/my_own_client/handlers.py
my_own_messenger/my_own_client/icon.ico
my_own_messenger/my_own_client/new_chat_gui.py
my_own_messenger/my_own_client/test_client.py
my_own_messenger/my_own_client/__pycache__/client.cpython-36.pyc
my_own_messenger/my_own_client/__pycache__/handlers.cpython-36.pyc
my_own_messenger/my_own_client/ui_forms/MyOwn.png
my_own_messenger/my_own_client/ui_forms/ab.gif
my_own_messenger/my_own_client/ui_forms/ac.gif
my_own_messenger/my_own_client/ui_forms/ai.gif
my_own_messenger/my_own_client/ui_forms/b.jpg
my_own_messenger/my_own_client/ui_forms/generic-avatar.png
my_own_messenger/my_own_client/ui_forms/i.jpg
my_own_messenger/my_own_client/ui_forms/icon.ico
my_own_messenger/my_own_client/ui_forms/login_page.ui
my_own_messenger/my_own_client/ui_forms/main.ui
my_own_messenger/my_own_client/ui_forms/new_chat.py
myownmessenger-0.1.dist-info/DESCRIPTION.rst
myownmessenger-0.1.dist-info/METADATA
myownmessenger-0.1.dist-info/RECORD
myownmessenger-0.1.dist-info/WHEEL
myownmessenger-0.1.dist-info/entry_points.txt
myownmessenger-0.1.dist-info/metadata.json
myownmessenger-0.1.dist-info/top_level.txt
