Metadata-Version: 2.0
Name: myownmessenger
Version: 0.1
Summary: My first messenger
Home-page: https://github.com/Rassoliny/MyOwnMess
Author: Rassoliny
Author-email: dimo120@yandex.ru
License: UNKNOWN
Platform: UNKNOWN
Requires-Python: >=3.6
Requires-Dist: PyQt5 (>=5.9)
Requires-Dist: SQLAlchemy (>=1.1.15)
